{
  "name": "Hyderabad",
  "time_table": [
    {
      "id": 1,
      "sehri": "04:38",
      "iftar": "6:35",
      "date": "24-4-2020",
      "day": "SAT"
    },
    {
      "id": 2,
      "sehri": "04:37",
      "iftar": "6:36",
      "date": "25-4-2020",
      "day": "SUN"
    },
    {
      "id": 3,
      "sehri": "04:36",
      "iftar": "6:36",
      "date": "26-4-2020",
      "day": "MON"
    },
    {
      "id": 4,
      "sehri": "04:36",
      "iftar": "6:36",
      "date": "27-4-2020",
      "day": "TUE"
    },
    {
      "id": 5,
      "sehri": "04:35",
      "iftar": "6:37",
      "date": "28-4-2020",
      "day": "WED"
    },
    {
      "id": 6,
      "sehri": "04:34",
      "iftar": "6:37",
      "date": "29-4-2020",
      "day": "THU"
    },
    {
      "id": 7,
      "sehri": "04:34",
      "iftar": "6:37",
      "date": "30-4-2020",
      "day": "FRI"
    },
    {
      "id": 8,
      "sehri": "04:33",
      "iftar": "6:37",
      "date": "01-05-2020",
      "day": "SAT"
    },
    {
      "id": 9,
      "sehri": "04:32",
      "iftar": "6:38",
      "date": "02-05-2020",
      "day": "SUN"
    },
    {
      "id": 10,
      "sehri": "04:31",
      "iftar": "6:38",
      "date": "03-05-2020",
      "day": "MON"
    },
    {
      "id": 11,
      "sehri": "04:31",
      "iftar": "6:38",
      "date": "04-05-2020",
      "day": "TUE"
    },
    {
      "id": 12,
      "sehri": "04:30",
      "iftar": "6:39",
      "date": "05-05-2020",
      "day": "WED"
    },
    {
      "id": 13,
      "sehri": "04:30",
      "iftar": "6:39",
      "date": "06-05-2020",
      "day": "THU"
    },
    {
      "id": 14,
      "sehri": "04:29",
      "iftar": "6:39",
      "date": "07-05-2020",
      "day": "FRI"
    },
    {
      "id": 15,
      "sehri": "04:28",
      "iftar": "6:40",
      "date": "08-05-2020",
      "day": "SAT"
    },
    {
      "id": 16,
      "sehri": "04:28",
      "iftar": "6:40",
      "date": "09-05-2020",
      "day": "SUN"
    },
    {
      "id": 17,
      "sehri": "04:27",
      "iftar": "6:40",
      "date": "10-5-2020",
      "day": "MON"
    },
    {
      "id": 6,
      "sehri": "04:27",
      "iftar": "6:41",
      "date": "11-5-2020",
      "day": "TUE"
    },
    {
      "id": 19,
      "sehri": "04:26",
      "iftar": "6:41",
      "date": "12-5-2020",
      "day": "WED"
    },
    {
      "id": 20,
      "sehri": "04:26",
      "iftar": "6:41",
      "date": "13-5-2020",
      "day": "THU"
    },
    {
      "id": 21,
      "sehri": "04:25",
      "iftar": "6:42",
      "date": "14-5-2020",
      "day": "FRI"
    },
    {
      "id": 22,
      "sehri": "04:25",
      "iftar": "6:42",
      "date": "15-5-2020",
      "day": "SAT"
    },
    {
      "id": 23,
      "sehri": "04:24",
      "iftar": "6:42",
      "date": "16-5-2020",
      "day": "SUN"
    },
    {
      "id": 24,
      "sehri": "04:24",
      "iftar": "6:43",
      "date": "17-5-2020",
      "day": "MON"
    },
    {
      "id": 25,
      "sehri": "04:23",
      "iftar": "6:43",
      "date": "6-5-2020",
      "day": "TUE"
    },
    {
      "id": 26,
      "sehri": "04:23",
      "iftar": "6:43",
      "date": "19-5-2020",
      "day": "WED"
    },
    {
      "id": 27,
      "sehri": "04:22",
      "iftar": "6:44",
      "date": "20-5-2020",
      "day": "THU"
    },
    {
      "id": 28,
      "sehri": "04:22",
      "iftar": "6:44",
      "date": "21-5-2020",
      "day": "FRI"
    },
    {
      "id": 29,
      "sehri": "04:22",
      "iftar": "6:45",
      "date": "22-5-2020",
      "day": "SAT"
    },
    {
      "id": 30,
      "sehri": "04:21",
      "iftar": "6:45",
      "date": "23-5-2020",
      "day": "SUN"
    }
  ]
}